pyconfbox_mongodb/__init__.py
pyconfbox_mongodb/storage.py
pyconfbox_mongodb-0.1.2.dist-info/METADATA
pyconfbox_mongodb-0.1.2.dist-info/WHEEL
pyconfbox_mongodb-0.1.2.dist-info/licenses/LICENSE
pyconfbox_mongodb-0.1.2.dist-info/RECORD
