Metadata-Version: 2.4
Name: pyconfbox-mongodb
Version: 0.1.2
Summary: MongoDB storage plugin for PyConfBox
Project-URL: Homepage, https://github.com/dan1901/pyconfbox
Project-URL: Documentation, https://github.com/dan1901/pyconfbox/tree/main/docs
Project-URL: Repository, https://github.com/dan1901/pyconfbox
Project-URL: Issues, https://github.com/dan1901/pyconfbox/issues
Author-email: Gabriel Ki <edc1901@gmail.com>
License: MIT License
License-File: LICENSE
Classifier: Development Status :: 4 - Beta
Classifier: Intended Audience :: Developers
Classifier: License :: OSI Approved :: MIT License
Classifier: Programming Language :: Python :: 3
Classifier: Programming Language :: Python :: 3.8
Classifier: Programming Language :: Python :: 3.9
Classifier: Programming Language :: Python :: 3.10
Classifier: Programming Language :: Python :: 3.11
Classifier: Programming Language :: Python :: 3.12
Classifier: Programming Language :: Python :: 3.13
Classifier: Topic :: Database
Classifier: Topic :: Software Development :: Libraries :: Python Modules
Requires-Python: >=3.8
Requires-Dist: pyconfbox>=0.1.2
Requires-Dist: pymongo>=4.0.0
